gym_qRacing/__init__.py
gym_qRacing/setup.py
gym_qRacing/envs/__init__.py
gym_qRacing/envs/race_simulation.py
gym_qRacing/envs/classes/__init__.py
gym_qRacing/envs/classes/agent_car.py
gym_qRacing/envs/classes/participant.py
gym_qRacing/envs/classes/sector.py
gym_qRacing/envs/classes/track.py
gym_qRacing/envs/functions/__init__.py
gym_qRacing/envs/functions/helper.py
gym_qRacing/envs/functions/logging.py
gym_qRacing/envs/models/__init__.py
gym_qRacing/envs/models/model_car.py
gym_qRacing/envs/models/model_lap.py
gym_qRacing/envs/models/model_overtaking.py
gym_qRacing/envs/models/model_pitstop.py
gym_qRacing/envs/models/model_startingGrid.py
gym_qRacing-0.0.12.dist-info/LICENSE
gym_qRacing-0.0.12.dist-info/METADATA
gym_qRacing-0.0.12.dist-info/WHEEL
gym_qRacing-0.0.12.dist-info/top_level.txt
gym_qRacing-0.0.12.dist-info/RECORD
