Metadata-Version: 2.1
Name: gym-qRacing
Version: 0.0.12
Summary: OpenAI Gym Environment for qRacing
Home-page: https://github.com/maxboettinger/gym-qRacing
Author: "Max Boettinger"
Author-email: max@bttngr.de
License: MIT
Project-URL: Bug Tracker, https://github.com/maxboettinger/gym-qRacing/issues
Project-URL: Documentation, https://github.com/maxboettinger/gym-qRacing/blob/main/README.md
Project-URL: Source Code, https://github.com/maxboettinger/gym-qRacing
Classifier: Development Status :: 5 - Production/Stable
Classifier: Environment :: Console
Classifier: Intended Audience :: Science/Research
Classifier: License :: OSI Approved :: MIT License
Classifier: Operating System :: MacOS
Classifier: Operating System :: Microsoft :: Windows
Classifier: Operating System :: POSIX :: Linux
Classifier: Programming Language :: Python
Classifier: Programming Language :: Python :: 3
Classifier: Programming Language :: Python :: 3 :: Only
Classifier: Programming Language :: Python :: 3.8
Classifier: Topic :: Scientific/Engineering
Classifier: Topic :: Scientific/Engineering :: Artificial Intelligence
Classifier: Natural Language :: Japanese
Classifier: Natural Language :: English
License-File: LICENSE
Requires-Dist: gym
Requires-Dist: numpy
Requires-Dist: matplotlib
Requires-Dist: rich
Requires-Dist: mlflow
Requires-Dist: pyyaml
